{"filename":"12699.JPG","pages":[{"regions":[{"bounding_box":{"fromX":56,"toX":1466,"fromY":55,"toY":266},"id":25642,"type":"staff","symbols":[{"bounding_box":{"fromX":88,"toX":161,"fromY":146,"toY":212},"agnostic_symbol_type":"clef.F","id":124435,"position_in_staff":"L3"},{"bounding_box":{"fromX":177,"toX":242,"fromY":124,"toY":236},"agnostic_symbol_type":"note.half_down","id":124436,"position_in_staff":"L4"},{"bounding_box":{"fromX":272,"toX":317,"fromY":118,"toY":238},"agnostic_symbol_type":"note.half_up","id":124437,"position_in_staff":"L2"},{"bounding_box":{"fromX":326,"toX":355,"fromY":141,"toY":221},"agnostic_symbol_type":"rest.longa2","id":124438,"position_in_staff":"L2"},{"bounding_box":{"fromX":355,"toX":375,"fromY":135,"toY":182},"agnostic_symbol_type":"rest.breve","id":124439,"position_in_staff":"L3"},{"bounding_box":{"fromX":371,"toX":393,"fromY":135,"toY":169},"agnostic_symbol_type":"rest.whole","id":124440,"position_in_staff":"L4"},{"bounding_box":{"fromX":408,"toX":459,"fromY":126,"toY":234},"agnostic_symbol_type":"note.quarter_down","id":124441,"position_in_staff":"L4"},{"bounding_box":{"fromX":477,"toX":543,"fromY":127,"toY":238},"agnostic_symbol_type":"note.eighth_down","id":124442,"position_in_staff":"L4"},{"bounding_box":{"fromX":544,"toX":616,"fromY":125,"toY":240},"agnostic_symbol_type":"note.eighth_down","id":124443,"position_in_staff":"L4"},{"bounding_box":{"fromX":623,"toX":685,"fromY":128,"toY":238},"agnostic_symbol_type":"note.half_down","id":124444,"position_in_staff":"L4"},{"bounding_box":{"fromX":678,"toX":702,"fromY":123,"toY":147},"agnostic_symbol_type":"dot","id":124445,"position_in_staff":"S4"},{"bounding_box":{"fromX":702,"toX":764,"fromY":126,"toY":239},"agnostic_symbol_type":"note.quarter_down","id":124446,"position_in_staff":"L4"},{"bounding_box":{"fromX":762,"toX":784,"fromY":125,"toY":155},"agnostic_symbol_type":"rest.half","id":124447,"position_in_staff":"L4"},{"bounding_box":{"fromX":791,"toX":820,"fromY":138,"toY":218},"agnostic_symbol_type":"rest.longa2","id":124448,"position_in_staff":"L2"},{"bounding_box":{"fromX":811,"toX":840,"fromY":136,"toY":213},"agnostic_symbol_type":"rest.longa2","id":124449,"position_in_staff":"L2"},{"bounding_box":{"fromX":835,"toX":856,"fromY":131,"toY":163},"agnostic_symbol_type":"rest.whole","id":124450,"position_in_staff":"L4"},{"bounding_box":{"fromX":892,"toX":938,"fromY":134,"toY":253},"agnostic_symbol_type":"note.quarter_up","id":124451,"position_in_staff":"S1"},{"bounding_box":{"fromX":934,"toX":958,"fromY":214,"toY":236},"agnostic_symbol_type":"dot","id":124452,"position_in_staff":"S1"},{"bounding_box":{"fromX":962,"toX":1008,"fromY":107,"toY":251},"agnostic_symbol_type":"note.eighth_up","id":124453,"position_in_staff":"S1"},{"bounding_box":{"fromX":1024,"toX":1079,"fromY":89,"toY":205},"agnostic_symbol_type":"note.quarter_down","id":124454,"position_in_staff":"L5"},{"bounding_box":{"fromX":1095,"toX":1156,"fromY":87,"toY":203},"agnostic_symbol_type":"note.eighth_down","id":124455,"position_in_staff":"L5"},{"bounding_box":{"fromX":1169,"toX":1236,"fromY":81,"toY":196},"agnostic_symbol_type":"note.eighth_down","id":124456,"position_in_staff":"L5"},{"bounding_box":{"fromX":1245,"toX":1307,"fromY":130,"toY":243},"agnostic_symbol_type":"note.half_down","id":124457,"position_in_staff":"S3"},{"bounding_box":{"fromX":1316,"toX":1363,"fromY":131,"toY":238},"agnostic_symbol_type":"note.half_down","id":124458,"position_in_staff":"S3"},{"bounding_box":{"fromX":1388,"toX":1453,"fromY":131,"toY":209},"agnostic_symbol_type":"custos","id":124459,"position_in_staff":"L2"}]},{"bounding_box":{"fromX":18,"toX":1444,"fromY":337,"toY":570},"id":25643,"type":"staff","symbols":[{"bounding_box":{"fromX":34,"toX":109,"fromY":422,"toY":493},"agnostic_symbol_type":"clef.F","id":124460,"position_in_staff":"L3"},{"bounding_box":{"fromX":136,"toX":156,"fromY":463,"toY":494},"agnostic_symbol_type":"rest.half","id":124461,"position_in_staff":"L2"},{"bounding_box":{"fromX":168,"toX":213,"fromY":388,"toY":516},"agnostic_symbol_type":"note.quarter_up","id":124462,"position_in_staff":"L2"},{"bounding_box":{"fromX":237,"toX":284,"fromY":396,"toY":511},"agnostic_symbol_type":"note.quarter_up","id":124463,"position_in_staff":"L2"},{"bounding_box":{"fromX":312,"toX":361,"fromY":401,"toY":517},"agnostic_symbol_type":"note.half_up","id":124464,"position_in_staff":"L2"},{"bounding_box":{"fromX":388,"toX":435,"fromY":399,"toY":516},"agnostic_symbol_type":"note.quarter_up","id":124465,"position_in_staff":"L2"},{"bounding_box":{"fromX":457,"toX":503,"fromY":404,"toY":516},"agnostic_symbol_type":"note.quarter_up","id":124466,"position_in_staff":"L2"},{"bounding_box":{"fromX":515,"toX":569,"fromY":521,"toY":570},"agnostic_symbol_type":"note.whole","id":124467,"position_in_staff":"S0"},{"bounding_box":{"fromX":578,"toX":629,"fromY":467,"toY":518},"agnostic_symbol_type":"note.whole","id":124468,"position_in_staff":"L2"},{"bounding_box":{"fromX":621,"toX":654,"fromY":453,"toY":549},"agnostic_symbol_type":"accidental.flat","id":124469,"position_in_staff":"L1"},{"bounding_box":{"fromX":662,"toX":716,"fromY":491,"toY":566},"agnostic_symbol_type":"note.breve","id":124470,"position_in_staff":"L1"},{"bounding_box":{"fromX":733,"toX":786,"fromY":431,"toY":484},"agnostic_symbol_type":"note.whole","id":124471,"position_in_staff":"L3"},{"bounding_box":{"fromX":793,"toX":814,"fromY":421,"toY":472},"agnostic_symbol_type":"rest.breve","id":124472,"position_in_staff":"L3"},{"bounding_box":{"fromX":823,"toX":867,"fromY":434,"toY":470},"agnostic_symbol_type":"rest.seminima","id":124473,"position_in_staff":"L3"},{"bounding_box":{"fromX":870,"toX":920,"fromY":424,"toY":540},"agnostic_symbol_type":"note.quarter_down","id":124474,"position_in_staff":"S3"},{"bounding_box":{"fromX":928,"toX":975,"fromY":377,"toY":496},"agnostic_symbol_type":"note.quarter_down","id":124475,"position_in_staff":"L5"},{"bounding_box":{"fromX":975,"toX":997,"fromY":371,"toY":396},"agnostic_symbol_type":"dot","id":124476,"position_in_staff":"S5"},{"bounding_box":{"fromX":983,"toX":1046,"fromY":393,"toY":507},"agnostic_symbol_type":"note.eighth_down","id":124477,"position_in_staff":"S4"},{"bounding_box":{"fromX":1055,"toX":1108,"fromY":401,"toY":517},"agnostic_symbol_type":"note.quarter_down","id":124478,"position_in_staff":"L4"},{"bounding_box":{"fromX":1117,"toX":1168,"fromY":423,"toY":532},"agnostic_symbol_type":"note.quarter_down","id":124479,"position_in_staff":"S3"},{"bounding_box":{"fromX":1190,"toX":1239,"fromY":405,"toY":516},"agnostic_symbol_type":"note.quarter_down","id":124480,"position_in_staff":"L4"},{"bounding_box":{"fromX":1255,"toX":1311,"fromY":434,"toY":549},"agnostic_symbol_type":"note.quarter_down","id":124481,"position_in_staff":"L3"},{"bounding_box":{"fromX":1328,"toX":1404,"fromY":347,"toY":412},"agnostic_symbol_type":"custos","id":124482,"position_in_staff":"L5"}]},{"bounding_box":{"fromX":14,"toX":1441,"fromY":633,"toY":858},"id":25644,"type":"staff"},{"bounding_box":{"fromX":14,"toX":1461,"fromY":915,"toY":1137},"id":25646,"type":"staff"},{"bounding_box":{"fromX":20,"toX":1466,"fromY":1213,"toY":1442},"id":25647,"type":"staff"},{"bounding_box":{"fromX":16,"toX":1463,"fromY":1512,"toY":1749},"id":25649,"type":"staff"},{"bounding_box":{"fromX":1553,"toX":2992,"fromY":47,"toY":302},"id":25653,"type":"staff"},{"bounding_box":{"fromX":1523,"toX":2987,"fromY":352,"toY":565},"id":25654,"type":"staff"},{"bounding_box":{"fromX":1529,"toX":2992,"fromY":636,"toY":870},"id":25655,"type":"staff","symbols":[{"bounding_box":{"fromX":1554,"toX":1628,"fromY":704,"toY":777},"agnostic_symbol_type":"clef.F","id":124483,"position_in_staff":"L3"},{"bounding_box":{"fromX":1640,"toX":1694,"fromY":708,"toY":761},"agnostic_symbol_type":"note.whole","id":124484,"position_in_staff":"L3"},{"bounding_box":{"fromX":1709,"toX":1771,"fromY":758,"toY":821},"agnostic_symbol_type":"note.breve","id":124485,"position_in_staff":"S1"},{"bounding_box":{"fromX":1781,"toX":1848,"fromY":707,"toY":773},"agnostic_symbol_type":"note.breve","id":124486,"position_in_staff":"L3"},{"bounding_box":{"fromX":1874,"toX":1929,"fromY":769,"toY":821},"agnostic_symbol_type":"note.whole","id":124487,"position_in_staff":"S1"},{"bounding_box":{"fromX":1946,"toX":2006,"fromY":694,"toY":765},"agnostic_symbol_type":"note.breve","id":124488,"position_in_staff":"S3"},{"bounding_box":{"fromX":2030,"toX":2086,"fromY":774,"toY":826},"agnostic_symbol_type":"note.whole","id":124489,"position_in_staff":"S1"},{"bounding_box":{"fromX":2105,"toX":2127,"fromY":739,"toY":795},"agnostic_symbol_type":"rest.breve","id":124490,"position_in_staff":"L2"},{"bounding_box":{"fromX":2153,"toX":2205,"fromY":741,"toY":793},"agnostic_symbol_type":"note.whole","id":124491,"position_in_staff":"S2"},{"bounding_box":{"fromX":2234,"toX":2285,"fromY":695,"toY":744},"agnostic_symbol_type":"note.whole","id":124492,"position_in_staff":"L4"},{"bounding_box":{"fromX":2312,"toX":2367,"fromY":719,"toY":768},"agnostic_symbol_type":"note.whole","id":124493,"position_in_staff":"S3"},{"bounding_box":{"fromX":2364,"toX":2388,"fromY":723,"toY":745},"agnostic_symbol_type":"dot","id":124494,"position_in_staff":"S3"},{"bounding_box":{"fromX":2381,"toX":2431,"fromY":667,"toY":780},"agnostic_symbol_type":"note.half_up","id":124495,"position_in_staff":"L3"},{"bounding_box":{"fromX":2454,"toX":2508,"fromY":746,"toY":798},"agnostic_symbol_type":"note.whole","id":124496,"position_in_staff":"S2"},{"bounding_box":{"fromX":2543,"toX":2599,"fromY":763,"toY":812},"agnostic_symbol_type":"note.whole","id":124497,"position_in_staff":"L2"},{"bounding_box":{"fromX":2626,"toX":2677,"fromY":674,"toY":794},"agnostic_symbol_type":"note.half_up","id":124498,"position_in_staff":"S2"},{"bounding_box":{"fromX":2704,"toX":2760,"fromY":667,"toY":777},"agnostic_symbol_type":"note.half_up","id":124499,"position_in_staff":"L3"},{"bounding_box":{"fromX":2762,"toX":2799,"fromY":764,"toY":858},"agnostic_symbol_type":"accidental.flat","id":124500,"position_in_staff":"L1"},{"bounding_box":{"fromX":2803,"toX":2848,"fromY":728,"toY":855},"agnostic_symbol_type":"note.half_up","id":124501,"position_in_staff":"L1"},{"bounding_box":{"fromX":2846,"toX":2870,"fromY":803,"toY":827},"agnostic_symbol_type":"dot","id":124502,"position_in_staff":"S1"},{"bounding_box":{"fromX":2868,"toX":2916,"fromY":712,"toY":833},"agnostic_symbol_type":"note.quarter_up","id":124503,"position_in_staff":"S1"},{"bounding_box":{"fromX":2914,"toX":2982,"fromY":733,"toY":807},"agnostic_symbol_type":"custos","id":124504,"position_in_staff":"L2"}]},{"bounding_box":{"fromX":1534,"toX":2990,"fromY":930,"toY":1185},"id":25657,"type":"staff","symbols":[{"bounding_box":{"fromX":1544,"toX":1614,"fromY":986,"toY":1067},"agnostic_symbol_type":"clef.F","id":124506,"position_in_staff":"L3"},{"bounding_box":{"fromX":1626,"toX":1669,"fromY":1041,"toY":1090},"agnostic_symbol_type":"note.whole","id":124507,"position_in_staff":"L2"},{"bounding_box":{"fromX":1703,"toX":1761,"fromY":1103,"toY":1153},"agnostic_symbol_type":"note.whole","id":124508,"position_in_staff":"L0"},{"bounding_box":{"fromX":1780,"toX":1806,"fromY":997,"toY":1074},"agnostic_symbol_type":"rest.longa2","id":124509,"position_in_staff":"L2"},{"bounding_box":{"fromX":1795,"toX":1829,"fromY":1002,"toY":1070},"agnostic_symbol_type":"rest.longa2","id":124511,"position_in_staff":"L2"},{"bounding_box":{"fromX":1817,"toX":1840,"fromY":996,"toY":1034},"agnostic_symbol_type":"rest.whole","id":124512,"position_in_staff":"L4"},{"bounding_box":{"fromX":1893,"toX":1954,"fromY":1101,"toY":1166},"agnostic_symbol_type":"note.breve","id":124513,"position_in_staff":"S0"},{"bounding_box":{"fromX":1964,"toX":2025,"fromY":1046,"toY":1112},"agnostic_symbol_type":"note.breve","id":124514,"position_in_staff":"L2"},{"bounding_box":{"fromX":2046,"toX":2108,"fromY":1103,"toY":1171},"agnostic_symbol_type":"note.breve","id":124515,"position_in_staff":"L0"},{"bounding_box":{"fromX":2117,"toX":2170,"fromY":1061,"toY":1118},"agnostic_symbol_type":"note.breve","id":124516,"position_in_staff":"S1"},{"bounding_box":{"fromX":2193,"toX":2253,"fromY":1008,"toY":1084},"agnostic_symbol_type":"note.breve","id":124517,"position_in_staff":"L3"},{"bounding_box":{"fromX":2289,"toX":2350,"fromY":1049,"toY":1119},"agnostic_symbol_type":"note.breve","id":124518,"position_in_staff":"L2"},{"bounding_box":{"fromX":2387,"toX":2498,"fromY":1035,"toY":1176},"agnostic_symbol_type":"ligature","id":124519,"position_in_staff":"S0"},{"bounding_box":{"fromX":2574,"toX":2743,"fromY":1045,"toY":1180},"agnostic_symbol_type":"note.tripleWholeStem_up","id":124522,"position_in_staff":"S0"},{"bounding_box":{"fromX":2587,"toX":2687,"fromY":1041,"toY":1107},"agnostic_symbol_type":"fermata.above","id":124521,"position_in_staff":"S2"},{"bounding_box":{"fromX":2723,"toX":2753,"fromY":975,"toY":1126},"agnostic_symbol_type":"verticalLine","id":124523,"position_in_staff":"L1"},{"bounding_box":{"fromX":2744,"toX":2770,"fromY":981,"toY":1128},"agnostic_symbol_type":"verticalLine","id":124524,"position_in_staff":"L1"}]},{"bounding_box":{"fromX":1520,"toX":2974,"fromY":1218,"toY":1477},"id":25658,"type":"staff","symbols":[{"bounding_box":{"fromX":1539,"toX":1612,"fromY":1283,"toY":1365},"agnostic_symbol_type":"clef.F","id":124525,"position_in_staff":"L3"},{"bounding_box":{"fromX":1637,"toX":1686,"fromY":1233,"toY":1400},"agnostic_symbol_type":"metersign.Ccut","id":124526,"position_in_staff":"L3"},{"bounding_box":{"fromX":1689,"toX":1713,"fromY":1285,"toY":1372},"agnostic_symbol_type":"rest.longa2","id":124527,"position_in_staff":"L2"},{"bounding_box":{"fromX":1746,"toX":1802,"fromY":1271,"toY":1389},"agnostic_symbol_type":"note.half_down","id":124528,"position_in_staff":"L4"},{"bounding_box":{"fromX":1791,"toX":1816,"fromY":1274,"toY":1297},"agnostic_symbol_type":"dot","id":124529,"position_in_staff":"S4"},{"bounding_box":{"fromX":1819,"toX":1872,"fromY":1295,"toY":1421},"agnostic_symbol_type":"note.quarter_down","id":124530,"position_in_staff":"S3"},{"bounding_box":{"fromX":1892,"toX":1944,"fromY":1313,"toY":1436},"agnostic_symbol_type":"note.quarter_down","id":124531,"position_in_staff":"L3"},{"bounding_box":{"fromX":1968,"toX":2023,"fromY":1281,"toY":1406},"agnostic_symbol_type":"note.quarter_down","id":124532,"position_in_staff":"L4"},{"bounding_box":{"fromX":2054,"toX":2111,"fromY":1348,"toY":1403},"agnostic_symbol_type":"note.whole","id":124533,"position_in_staff":"L2"},{"bounding_box":{"fromX":2130,"toX":2193,"fromY":1409,"toY":1474},"agnostic_symbol_type":"accidental.sharp","id":124535,"position_in_staff":"L0"},{"bounding_box":{"fromX":2134,"toX":2192,"fromY":1298,"toY":1418},"agnostic_symbol_type":"note.half_up","id":124534,"position_in_staff":"S1"},{"bounding_box":{"fromX":2221,"toX":2273,"fromY":1346,"toY":1401},"agnostic_symbol_type":"note.whole","id":124536,"position_in_staff":"L2"},{"bounding_box":{"fromX":2292,"toX":2312,"fromY":1334,"toY":1373},"agnostic_symbol_type":"rest.whole","id":124537,"position_in_staff":"L3"},{"bounding_box":{"fromX":2342,"toX":2393,"fromY":1353,"toY":1406},"agnostic_symbol_type":"note.whole","id":124538,"position_in_staff":"L2"},{"bounding_box":{"fromX":2416,"toX":2469,"fromY":1284,"toY":1337},"agnostic_symbol_type":"note.whole","id":124539,"position_in_staff":"L4"},{"bounding_box":{"fromX":2484,"toX":2595,"fromY":1269,"toY":1427},"agnostic_symbol_type":"metersign.CcutZ","id":124540,"position_in_staff":"L3"},{"bounding_box":{"fromX":2594,"toX":2620,"fromY":1310,"toY":1397},"agnostic_symbol_type":"rest.longa2","id":124541,"position_in_staff":"L2"},{"bounding_box":{"fromX":2648,"toX":2708,"fromY":1310,"toY":1361},"agnostic_symbol_type":"note.whole","id":124542,"position_in_staff":"S3"},{"bounding_box":{"fromX":2699,"toX":2725,"fromY":1321,"toY":1346},"agnostic_symbol_type":"dot","id":124543,"position_in_staff":"S3"},{"bounding_box":{"fromX":2728,"toX":2787,"fromY":1313,"toY":1438},"agnostic_symbol_type":"note.half_down","id":124544,"position_in_staff":"S3"},{"bounding_box":{"fromX":2812,"toX":2865,"fromY":1310,"toY":1360},"agnostic_symbol_type":"note.whole","id":124545,"position_in_staff":"S3"},{"bounding_box":{"fromX":2867,"toX":2950,"fromY":1256,"toY":1333},"agnostic_symbol_type":"custos","id":124546,"position_in_staff":"L4"}]},{"bounding_box":{"fromX":1503,"toX":2957,"fromY":1510,"toY":1760},"id":25661,"type":"staff","symbols":[{"bounding_box":{"fromX":1517,"toX":1595,"fromY":1556,"toY":1645},"agnostic_symbol_type":"clef.F","id":124547,"position_in_staff":"L3"},{"bounding_box":{"fromX":1606,"toX":1627,"fromY":1561,"toY":1649},"agnostic_symbol_type":"rest.longa2","id":124548,"position_in_staff":"L2"},{"bounding_box":{"fromX":1620,"toX":1641,"fromY":1569,"toY":1648},"agnostic_symbol_type":"rest.longa2","id":124549,"position_in_staff":"L2"},{"bounding_box":{"fromX":1644,"toX":1667,"fromY":1541,"toY":1609},"agnostic_symbol_type":"rest.longa2","id":124550,"position_in_staff":"L3"},{"bounding_box":{"fromX":1661,"toX":1681,"fromY":1541,"toY":1616},"agnostic_symbol_type":"rest.longa2","id":124551,"position_in_staff":"L3"},{"bounding_box":{"fromX":1713,"toX":1761,"fromY":1557,"toY":1613},"agnostic_symbol_type":"note.whole","id":124552,"position_in_staff":"L4"},{"bounding_box":{"fromX":1758,"toX":1786,"fromY":1556,"toY":1582},"agnostic_symbol_type":"dot","id":124553,"position_in_staff":"S4"},{"bounding_box":{"fromX":1797,"toX":1852,"fromY":1583,"toY":1699},"agnostic_symbol_type":"note.half_down","id":124554,"position_in_staff":"S3"},{"bounding_box":{"fromX":1874,"toX":1924,"fromY":1597,"toY":1643},"agnostic_symbol_type":"note.whole","id":124555,"position_in_staff":"L3"},{"bounding_box":{"fromX":1950,"toX":2000,"fromY":1605,"toY":1669},"agnostic_symbol_type":"note.breve","id":124556,"position_in_staff":"S2"},{"bounding_box":{"fromX":2046,"toX":2097,"fromY":1569,"toY":1615},"agnostic_symbol_type":"note.whole","id":124557,"position_in_staff":"L4"},{"bounding_box":{"fromX":2119,"toX":2179,"fromY":1582,"toY":1644},"agnostic_symbol_type":"note.breve","id":124558,"position_in_staff":"S3"},{"bounding_box":{"fromX":2222,"toX":2270,"fromY":1665,"toY":1710},"agnostic_symbol_type":"note.whole","id":124559,"position_in_staff":"S1"},{"bounding_box":{"fromX":2293,"toX":2347,"fromY":1591,"toY":1654},"agnostic_symbol_type":"note.breve","id":124560,"position_in_staff":"S3"},{"bounding_box":{"fromX":2350,"toX":2370,"fromY":1598,"toY":1627},"agnostic_symbol_type":"dot","id":124561,"position_in_staff":"L4"},{"bounding_box":{"fromX":2379,"toX":2404,"fromY":1598,"toY":1688},"agnostic_symbol_type":"rest.longa2","id":124562,"position_in_staff":"L2"},{"bounding_box":{"fromX":2402,"toX":2428,"fromY":1602,"toY":1644},"agnostic_symbol_type":"rest.breve","id":124563,"position_in_staff":"L3"},{"bounding_box":{"fromX":2460,"toX":2518,"fromY":1670,"toY":1721},"agnostic_symbol_type":"note.whole","id":124564,"position_in_staff":"S1"},{"bounding_box":{"fromX":2545,"toX":2597,"fromY":1677,"toY":1725},"agnostic_symbol_type":"note.whole","id":124565,"position_in_staff":"S1"},{"bounding_box":{"fromX":2608,"toX":2662,"fromY":1678,"toY":1725},"agnostic_symbol_type":"note.whole","id":124566,"position_in_staff":"S1"},{"bounding_box":{"fromX":2673,"toX":2726,"fromY":1601,"toY":1666},"agnostic_symbol_type":"note.breve","id":124567,"position_in_staff":"S3"},{"bounding_box":{"fromX":2748,"toX":2802,"fromY":1567,"toY":1619},"agnostic_symbol_type":"note.whole","id":124568,"position_in_staff":"L5"},{"bounding_box":{"fromX":2825,"toX":2896,"fromY":1566,"toY":1651},"agnostic_symbol_type":"custos","id":124569,"position_in_staff":"S3"}]},{"bounding_box":{"fromX":139,"toX":1439,"fromY":256,"toY":354},"id":25662,"type":"lyrics"},{"bounding_box":{"fromX":53,"toX":1413,"fromY":539,"toY":658},"id":25663,"type":"lyrics"},{"bounding_box":{"fromX":38,"toX":1455,"fromY":820,"toY":945},"id":25665,"type":"lyrics"},{"bounding_box":{"fromX":67,"toX":1399,"fromY":1099,"toY":1235},"id":25667,"type":"lyrics"},{"bounding_box":{"fromX":113,"toX":1376,"fromY":1387,"toY":1523},"id":25668,"type":"lyrics"},{"bounding_box":{"fromX":55,"toX":1410,"fromY":1710,"toY":1853},"id":25669,"type":"lyrics"},{"bounding_box":{"fromX":1722,"toX":2858,"fromY":245,"toY":383},"id":25671,"type":"lyrics"},{"bounding_box":{"fromX":1758,"toX":2935,"fromY":534,"toY":679},"id":25672,"type":"lyrics"},{"bounding_box":{"fromX":1566,"toX":2873,"fromY":813,"toY":956},"id":25673,"type":"lyrics"},{"bounding_box":{"fromX":1593,"toX":2761,"fromY":1139,"toY":1242},"id":25674,"type":"lyrics"},{"bounding_box":{"fromX":1610,"toX":2946,"fromY":1398,"toY":1547},"id":25675,"type":"lyrics"},{"bounding_box":{"fromX":1626,"toX":2524,"fromY":1686,"toY":1831},"id":25677,"type":"lyrics"}],"bounding_box":{"fromX":0,"toX":3000,"fromY":0,"toY":2030},"id":2994}],"id":3116}